odoo8_addon_business_requirement_deliverable_project-8.0.4.0.6-py2.7-nspkg.pth
odoo8_addon_business_requirement_deliverable_project-8.0.4.0.6.dist-info/DESCRIPTION.rst
odoo8_addon_business_requirement_deliverable_project-8.0.4.0.6.dist-info/METADATA
odoo8_addon_business_requirement_deliverable_project-8.0.4.0.6.dist-info/RECORD
odoo8_addon_business_requirement_deliverable_project-8.0.4.0.6.dist-info/WHEEL
odoo8_addon_business_requirement_deliverable_project-8.0.4.0.6.dist-info/metadata.json
odoo8_addon_business_requirement_deliverable_project-8.0.4.0.6.dist-info/namespace_packages.txt
odoo8_addon_business_requirement_deliverable_project-8.0.4.0.6.dist-info/top_level.txt
odoo_addons/business_requirement_deliverable_project/README.rst
odoo_addons/business_requirement_deliverable_project/__init__.py
odoo_addons/business_requirement_deliverable_project/__openerp__.py
odoo_addons/business_requirement_deliverable_project/i18n/sl.po
odoo_addons/business_requirement_deliverable_project/models/__init__.py
odoo_addons/business_requirement_deliverable_project/models/business.py
odoo_addons/business_requirement_deliverable_project/models/project.py
odoo_addons/business_requirement_deliverable_project/static/description/icon.png
odoo_addons/business_requirement_deliverable_project/static/img/bus_req_project.png
odoo_addons/business_requirement_deliverable_project/tests/__init__.py
odoo_addons/business_requirement_deliverable_project/tests/test_br.py
odoo_addons/business_requirement_deliverable_project/views/business_view.xml
odoo_addons/business_requirement_deliverable_project/wizard/__init__.py
odoo_addons/business_requirement_deliverable_project/wizard/generate_projects.py
odoo_addons/business_requirement_deliverable_project/wizard/generate_projects_view.xml
